typedmarshal/__init__.py
typedmarshal/model.py
typedmarshal/util.py
typedmarshal-0.0.1.dist-info/METADATA
typedmarshal-0.0.1.dist-info/RECORD
typedmarshal-0.0.1.dist-info/WHEEL
typedmarshal-0.0.1.dist-info/top_level.txt
