Metadata-Version: 2.1
Name: typedmarshal
Version: 0.0.1
Summary: Strongly typed JSON (un)marshal library
Home-page: https://github.com/puhitaku/typedmarshal
Author: Takumi Sueda
Author-email: puhitaku@gmail.com
License: BSD License
Platform: UNKNOWN
Classifier: Development Status :: 2 - Pre-Alpha
Classifier: Intended Audience :: Developers
Classifier: License :: OSI Approved :: BSD License
Classifier: Operating System :: OS Independent
Classifier: Programming Language :: Python
Classifier: Programming Language :: Python :: 3.6
Classifier: Programming Language :: JavaScript
Classifier: Topic :: Software Development :: Libraries :: Python Modules
